amniotic/__init__.py
amniotic/api.py
amniotic/client.py
amniotic/controls.py
amniotic/device.py
amniotic/doc_sb.py
amniotic/entrypoint.py
amniotic/ha_api.py
amniotic/obs.py
amniotic/paths.py
amniotic/project.py
amniotic/recording.py
amniotic/sapi_sb.py
amniotic/settings.py
amniotic/theme.py
amniotic/version
amniotic/version.py
amniotic/v0/__init__.py
amniotic/v0/audio.py
amniotic/v0/config.py
amniotic/v0/control.py
amniotic/v0/device.py
amniotic/v0/loop.py
amniotic/v0/sensor.py
amniotic/v0/start.py
amniotic/v0/tools.py
amniotic-1.5.14.data/scripts/vlc-tn.service
amniotic-1.5.14.dist-info/METADATA
amniotic-1.5.14.dist-info/WHEEL
amniotic-1.5.14.dist-info/entry_points.txt
amniotic-1.5.14.dist-info/top_level.txt
amniotic-1.5.14.dist-info/RECORD
