Metadata-Version: 2.4
Name: amniotic
Version: 1.5.14
Summary: A multi-output ambient sound mixer for Home Assistant
Home-page: https://github.com/None/amniotic
Author: Frontmatter
Author-email: innovative.fowler@mask.pro.fmtr.dev
License: Copyright © 2026 Frontmatter. All rights reserved.
Keywords: ambient sound audio white noise masking sleep
Requires-Dist: fmtr.tools[api,av,caching,debug,ha.api,http,logging,mqtt,path.app,sets,tabular,version.dev,yaml,youtube]
Requires-Dist: haco
Provides-Extra: all
Dynamic: author
Dynamic: author-email
Dynamic: description
Dynamic: description-content-type
Dynamic: home-page
Dynamic: keywords
Dynamic: license
Dynamic: provides-extra
Dynamic: requires-dist
Dynamic: summary
